pyffish.cpython-312-darwin.so
pyffish-0.0.88.dist-info/RECORD
pyffish-0.0.88.dist-info/WHEEL
pyffish-0.0.88.dist-info/top_level.txt
pyffish-0.0.88.dist-info/METADATA
pyffish-0.0.88.dist-info/licenses/AUTHORS
